alibabacloud_oos20190601/__init__.py
alibabacloud_oos20190601/client.py
alibabacloud_oos20190601/models/__init__.py
alibabacloud_oos20190601/models/_analyze_git_repository_request.py
alibabacloud_oos20190601/models/_analyze_git_repository_response.py
alibabacloud_oos20190601/models/_analyze_git_repository_response_body.py
alibabacloud_oos20190601/models/_cancel_execution_request.py
alibabacloud_oos20190601/models/_cancel_execution_response.py
alibabacloud_oos20190601/models/_cancel_execution_response_body.py
alibabacloud_oos20190601/models/_change_resource_group_request.py
alibabacloud_oos20190601/models/_change_resource_group_response.py
alibabacloud_oos20190601/models/_change_resource_group_response_body.py
alibabacloud_oos20190601/models/_check_git_repo_file_exists_request.py
alibabacloud_oos20190601/models/_check_git_repo_file_exists_response.py
alibabacloud_oos20190601/models/_check_git_repo_file_exists_response_body.py
alibabacloud_oos20190601/models/_check_git_repository_exists_request.py
alibabacloud_oos20190601/models/_check_git_repository_exists_response.py
alibabacloud_oos20190601/models/_check_git_repository_exists_response_body.py
alibabacloud_oos20190601/models/_continue_deploy_application_group_request.py
alibabacloud_oos20190601/models/_continue_deploy_application_group_response.py
alibabacloud_oos20190601/models/_continue_deploy_application_group_response_body.py
alibabacloud_oos20190601/models/_create_application_group_request.py
alibabacloud_oos20190601/models/_create_application_group_response.py
alibabacloud_oos20190601/models/_create_application_group_response_body.py
alibabacloud_oos20190601/models/_create_application_request.py
alibabacloud_oos20190601/models/_create_application_response.py
alibabacloud_oos20190601/models/_create_application_response_body.py
alibabacloud_oos20190601/models/_create_application_shrink_request.py
alibabacloud_oos20190601/models/_create_git_repository_request.py
alibabacloud_oos20190601-3.6.0.dist-info/LICENSE
alibabacloud_oos20190601-3.6.0.dist-info/METADATA
alibabacloud_oos20190601-3.6.0.dist-info/WHEEL
alibabacloud_oos20190601-3.6.0.dist-info/top_level.txt
alibabacloud_oos20190601-3.6.0.dist-info/RECORD
